Metadata-Version: 1.1
Name: behzodcalculator
Version: 0.0.1
Summary: Juda oddiy kalkulyator
Home-page: UNKNOWN
Author: Asliddinov Behzod
Author-email: uzpythonistadeveloper@gmail.com
License: MIT
Keywords: calculator
Platform: UNKNOWN
Classifier: Development Status :: 5 - Production/Stable
Classifier: Intended Audience :: Education
Classifier: Operating System :: Microsoft :: Windows :: Windows 10
Classifier: License :: OSI Approved :: MIT License
Classifier: Programming Language :: Python :: 3
